chefkoch/__init__.py
chefkoch/version.py
chefkoch-0.0.dist-info/LICENSE
chefkoch-0.0.dist-info/METADATA
chefkoch-0.0.dist-info/WHEEL
chefkoch-0.0.dist-info/top_level.txt
chefkoch-0.0.dist-info/RECORD
