Metadata-Version: 2.1
Name: chefkoch
Version: 0.0
Summary: A compute cluster cuisine for distributed scientific computing in python
Home-page: https://ems-tu-ilmenau.github.io/ćhefkoch/
Author: Christoph Wagner, EMS group TU Ilmenau
Author-email: christoph.wagner@tu-ilmenau.de
License: Apache Software License
Keywords: compute cluster HPC LSF dask parallel computing scheduler framework
Platform: UNKNOWN
Classifier: Development Status :: 1 - Planning
Classifier: Intended Audience :: Developers
Classifier: Intended Audience :: Education
Classifier: Intended Audience :: Science/Research
Classifier: Intended Audience :: Information Technology
Classifier: License :: OSI Approved :: Apache Software License
Classifier: Natural Language :: English
Classifier: Operating System :: Microsoft :: Windows
Classifier: Operating System :: POSIX :: Linux
Classifier: Operating System :: MacOS :: MacOS X
Classifier: Programming Language :: Python
Classifier: Programming Language :: Python :: 2
Classifier: Programming Language :: Python :: 2.7
Classifier: Programming Language :: Python :: 3
Classifier: Programming Language :: Python :: 3.5
Classifier: Programming Language :: Python :: 3.6
Classifier: Programming Language :: Python :: 3.7
Classifier: Topic :: Scientific/Engineering
Classifier: Topic :: Software Development
Classifier: Topic :: System :: Distributed Computing
Requires-Dist: dask (>=1.0.0)
Requires-Dist: six
Requires-Dist: dask-jobqueue (>=0.4.1)
